{
  "main": {
    "id": "f986da1263112140",
    "type": "split",
    "children": [
      {
        "id": "79f93ae95ed2b012",
        "type": "tabs",
        "children": [
          {
            "id": "716976ae69cf2479",
            "type": "leaf",
            "state": {
              "type": "markdown",
              "state": {
                "file": "Obsidian/ComputerScience/선형대수학/06. 벡터/무제 파일.md",
                "mode": "source",
                "source": false
              }
            }
          }
        ]
      },
      {
        "id": "c19bb4aac09529f6",
        "type": "tabs",
        "children": [
          {
            "id": "c36178d730f484a8",
            "type": "leaf",
            "state": {
              "type": "pdf",
              "state": {
                "file": "Obsidian/ComputerScience/선형대수학/06. 벡터/06. 백터.pdf"
              }
            }
          }
        ]
      }
    ],
    "direction": "vertical"
  },
  "left": {
    "id": "e6846e88925d1f6e",
    "type": "split",
    "children": [
      {
        "id": "3690d7f713394d67",
        "type": "tabs",
        "children": [
          {
            "id": "ba9e23474eb62275",
            "type": "leaf",
            "state": {
              "type": "file-explorer",
              "state": {
                "sortOrder": "alphabetical"
              }
            }
          },
          {
            "id": "00728ea3c734214e",
            "type": "leaf",
            "state": {
              "type": "search",
              "state": {
                "query": "",
                "matchingCase": false,
                "explainSearch": false,
                "collapseAll": false,
                "extraContext": false,
                "sortOrder": "alphabetical"
              }
            }
          },
          {
            "id": "1c7e08013834b2c8",
            "type": "leaf",
            "state": {
              "type": "bookmarks",
              "state": {}
            }
          }
        ]
      }
    ],
    "direction": "horizontal",
    "width": 240.5,
    "collapsed": true
  },
  "right": {
    "id": "67c0be972fb46913",
    "type": "split",
    "children": [
      {
        "id": "591cdf66caacdc0e",
        "type": "tabs",
        "children": [
          {
            "id": "a419b531493f0f6a",
            "type": "leaf",
            "state": {
              "type": "backlink",
              "state": {
                "file": "Obsidian/ComputerScience/선형대수학/06. 벡터/06. 백터.pdf",
                "collapseAll": false,
                "extraContext": false,
                "sortOrder": "alphabetical",
                "showSearch": false,
                "searchQuery": "",
                "backlinkCollapsed": false,
                "unlinkedCollapsed": true
              }
            }
          },
          {
            "id": "629294b686e53e5b",
            "type": "leaf",
            "state": {
              "type": "outgoing-link",
              "state": {
                "file": "Obsidian/ComputerScience/선형대수학/06. 벡터/06. 백터.pdf",
                "linksCollapsed": false,
                "unlinkedCollapsed": true
              }
            }
          },
          {
            "id": "26b7a6beaeb2bfed",
            "type": "leaf",
            "state": {
              "type": "tag",
              "state": {
                "sortOrder": "frequency",
                "useHierarchy": true
              }
            }
          },
          {
            "id": "86532e08d94fe6a9",
            "type": "leaf",
            "state": {
              "type": "outline",
              "state": {
                "file": "Obsidian/ComputerScience/선형대수학/06. 벡터/06. 백터.pdf"
              }
            }
          }
        ]
      }
    ],
    "direction": "horizontal",
    "width": 300,
    "collapsed": true
  },
  "left-ribbon": {
    "hiddenItems": {
      "switcher:퀵 스위처 열기": false,
      "graph:그래프 뷰 열기": false,
      "canvas:새 캔버스 만들기": false,
      "daily-notes:오늘의 데일리 노트 열기": false,
      "templates:템플릿 삽입": false,
      "command-palette:명령어 팔레트 열기": false
    }
  },
  "active": "c36178d730f484a8",
  "lastOpenFiles": [
    "Obsidian/ComputerScience/선형대수학/06. 벡터/무제 파일.md",
    "Obsidian/ComputerScience/선형대수학/06. 벡터/06. 백터.pdf",
    "Obsidian/ComputerScience/코딩 기초와 문제해결/3. 알고리즘과 프로그래밍 언어/순서도작성_예.pdf",
    "Obsidian/ComputerScience/코딩 기초와 문제해결/3. 알고리즘과 프로그래밍 언어/순서도 작성.md",
    "Obsidian/ComputerScience/코딩 기초와 문제해결/5. 함수/함수.pdf",
    "image/풀업_컨먼캐소드_led제어.jpg",
    "image/풀업_컨먼애노드_led제어.jpg",
    "image/풀다운_컨먼캐소드_led제어.jpg",
    "image/풀다운_컨먼애노드_led제어.jpg",
    "image/자동차 헤드라이트 시스템.jpg",
    "Obsidian/ComputerScience/코딩 기초와 문제해결/3. 알고리즘과 프로그래밍 언어/간단한 대화형 인공지능.pdf",
    "Obsidian/ComputerScience/코딩 기초와 문제해결/3. 알고리즘과 프로그래밍 언어/스크래치.pdf",
    "Obsidian/ComputerScience/코딩 기초와 문제해결/4. 아두이누/아두이노 실습.md",
    "Obsidian/ComputerScience/코딩 기초와 문제해결/5. 함수",
    "자동차 헤드라이트 시스템.jpg",
    "Obsidian/ComputerScience/코딩 기초와 문제해결/4. 아두이누/아두이노 입출력.md",
    "Obsidian/ComputerScience/코딩 기초와 문제해결/4. 아두이누/2. 아두이노 입력 이해하기.pdf",
    "Obsidian/ComputerScience/코딩 기초와 문제해결/4. 아두이누/1. 아두이노 출력.pdf",
    "Obsidian/ComputerScience/선형대수학/06. 벡터/chapter 6 연습문제.pdf",
    "Obsidian/ComputerScience/선형대수학/05. 행렬식/chapter 5 연습문제.pdf",
    "Obsidian/ComputerScience/코딩 기초와 문제해결/4. 아두이누/Led제어.md",
    "Obsidian/ComputerScience/코딩 기초와 문제해결/4. 아두이누/풀다운_컨먼애노드_led제어.jpg",
    "Obsidian/ComputerScience/코딩 기초와 문제해결/4. 아두이누/풀다운_컨먼캐소드_led제어.jpg",
    "Obsidian/ComputerScience/코딩 기초와 문제해결/4. 아두이누/풀업_컨먼애노드_led제어.jpg",
    "Obsidian/ComputerScience/코딩 기초와 문제해결/4. 아두이누/풀업_컨먼캐소드_led제어.jpg",
    "Obsidian/ComputerScience/코딩 기초와 문제해결/3. 알고리즘과 프로그래밍 언어/전역변수, 지역변수.md",
    "Obsidian/ComputerScience/코딩 기초와 문제해결/3. 알고리즘과 프로그래밍 언어/변수와 배열.md",
    "Obsidian/ComputerScience/코딩 기초와 문제해결/3. 알고리즘과 프로그래밍 언어/연산자.md",
    "Obsidian/ComputerScience/코딩 기초와 문제해결/3. 알고리즘과 프로그래밍 언어/문법.md",
    "Obsidian/ComputerScience/선형대수학/03. 행렬/외울거.md",
    "Obsidian/ComputerScience/선형대수학/02. 선형방정식/선형방정식.md",
    "Obsidian/ComputerScience/컴퓨터 구조/3. 중앙 처리 장치/2. 산술 논리 연산 장치.md",
    "Obsidian/ComputerScience/컴퓨터 구조/3. 중앙 처리 장치/4. 컴퓨터 명령어.md",
    "Obsidian/ComputerScience/웹프로그래밍/7. 웹 시스템 제작/문제 풀이.md",
    "Obsidian/ComputerScience/코딩 기초와 문제해결/중간고사.md",
    "Obsidian/index.md",
    "Obsidian/Welcome.md",
    "2024-06-25.md",
    "Obsidian/ComputerScience/코딩 기초와 문제해결/1. 컴퓨터에서의 정보의 표현/컴퓨터에서의 정보의 표현(시험문제 안나옴).md",
    "Obsidian/KR_history/고대/삼국시대/신라.md",
    "Obsidian/KR_history/고대/삼국시대/백제.md",
    "Obsidian/KR_history/고대/삼국시대/가야.md",
    "Obsidian/KR_history/고대/삼국시대/고구려.md",
    "Obsidian/KR_history/고대/남북국시대/발해.md",
    "Obsidian/KR_history/고대/남북국시대/통일신라.md"
  ]
}