{
  "main": {
    "id": "c18b2700cdefe54e",
    "type": "split",
    "children": [
      {
        "id": "0186311d740f722a",
        "type": "tabs",
        "children": [
          {
            "id": "3c5b6ef7162c8589",
            "type": "leaf",
            "state": {
              "type": "markdown",
              "state": {
                "file": "obsidian/ComputerScience/확률과 통계/20.mle/파라미터 추정.md",
                "mode": "source",
                "source": false
              }
            }
          },
          {
            "id": "fbb95d624c9f8987",
            "type": "leaf",
            "state": {
              "type": "markdown",
              "state": {
                "file": "obsidian/ComputerScience/확률과 통계/20.mle/MLE.md",
                "mode": "source",
                "source": false
              }
            }
          }
        ],
        "currentTab": 1
      }
    ],
    "direction": "vertical"
  },
  "left": {
    "id": "d4ef660eefc9dce8",
    "type": "split",
    "children": [
      {
        "id": "6a40ddeab999d131",
        "type": "tabs",
        "children": [
          {
            "id": "4824d7b5ee6b90fb",
            "type": "leaf",
            "state": {
              "type": "file-explorer",
              "state": {
                "sortOrder": "alphabetical"
              }
            }
          },
          {
            "id": "7cea1b4cbc945680",
            "type": "leaf",
            "state": {
              "type": "search",
              "state": {
                "query": "",
                "matchingCase": false,
                "explainSearch": false,
                "collapseAll": false,
                "extraContext": false,
                "sortOrder": "alphabetical"
              }
            }
          },
          {
            "id": "998b39b375eb1994",
            "type": "leaf",
            "state": {
              "type": "bookmarks",
              "state": {}
            }
          }
        ]
      }
    ],
    "direction": "horizontal",
    "width": 244.5
  },
  "right": {
    "id": "7955a80cb3f4ce08",
    "type": "split",
    "children": [
      {
        "id": "74a2a58bda4cda75",
        "type": "tabs",
        "children": [
          {
            "id": "d44099825c849e5a",
            "type": "leaf",
            "state": {
              "type": "backlink",
              "state": {
                "file": "obsidian/ComputerScience/확률과 통계/20.mle/파라미터 추정.md",
                "collapseAll": false,
                "extraContext": false,
                "sortOrder": "alphabetical",
                "showSearch": false,
                "searchQuery": "",
                "backlinkCollapsed": false,
                "unlinkedCollapsed": true
              }
            }
          },
          {
            "id": "d0d8bbe68caebe73",
            "type": "leaf",
            "state": {
              "type": "outgoing-link",
              "state": {
                "file": "obsidian/ComputerScience/확률과 통계/20.mle/파라미터 추정.md",
                "linksCollapsed": false,
                "unlinkedCollapsed": true
              }
            }
          },
          {
            "id": "6ddf4ffb0a43ab89",
            "type": "leaf",
            "state": {
              "type": "tag",
              "state": {
                "sortOrder": "frequency",
                "useHierarchy": true
              }
            }
          },
          {
            "id": "e26efddcf6394f13",
            "type": "leaf",
            "state": {
              "type": "outline",
              "state": {
                "file": "obsidian/ComputerScience/확률과 통계/20.mle/파라미터 추정.md"
              }
            }
          }
        ],
        "currentTab": 1
      }
    ],
    "direction": "horizontal",
    "width": 200,
    "collapsed": true
  },
  "left-ribbon": {
    "hiddenItems": {
      "switcher:퀵 스위처 열기": false,
      "graph:그래프 뷰 열기": false,
      "canvas:새 캔버스 만들기": false,
      "daily-notes:오늘의 데일리 노트 열기": false,
      "templates:템플릿 삽입": false,
      "command-palette:명령어 팔레트 열기": false,
      "obsidian-excalidraw-plugin:Create new drawing": false,
      "templater-obsidian:Templater": false
    }
  },
  "active": "4824d7b5ee6b90fb",
  "lastOpenFiles": [
    "obsidian/ComputerScience/확률과 통계/20.mle/파라미터 추정.md",
    "obsidian/ComputerScience/확률과 통계/20.mle/MLE.md",
    "obsidian/ComputerScience/확률과 통계/20.mle/Maximum Likelihood Estimation.md",
    "obsidian/ComputerScience/확률과 통계/20.mle/20_mle.pdf",
    "obsidian/index.md",
    "obsidian/ComputerScience/확률과 통계/14.Conditional_expectation/14_conditional_expectation.pdf",
    "obsidian/ComputerScience/확률과 통계/14.Conditional_expectation/Conditional Expectation.md",
    "obsidian/ComputerScience/확률과 통계/19.sampling_bootstrap/19_sampling_bootstrap.pdf",
    "obsidian/ComputerScience/확률과 통계/17.Continous_joint_probability-2/17_continous_joint_probability_iI.pdf",
    "obsidian/ComputerScience/웹프로그래밍/6. HTML 기초2/6장_확인문제_현재3번까지.pdf",
    "obsidian/ComputerScience/웹프로그래밍/4. 쿠키와 세션/4장_확인문제.pdf",
    "obsidian/ComputerScience/웹프로그래밍/6. HTML 기초2/HTML 기초 실습 2.pdf",
    "obsidian/ComputerScience/웹프로그래밍/4. 쿠키와 세션/쿠키와 세션.md",
    "obsidian/ComputerScience/웹프로그래밍/3. Spring Boot 기초/Spring Boot 기초 실습.md",
    "obsidian/ComputerScience/웹프로그래밍/4. 쿠키와 세션/확인문제.md",
    "obsidian/ComputerScience/웹프로그래밍/연습장.md",
    "obsidian/ComputerScience/웹프로그래밍/6. HTML 기초2/HTML 기초 실습2.md",
    "obsidian/ComputerScience/인공지능/5. CNN/실습/CNN (실습).pdf",
    "obsidian/ComputerScience/인공지능/5. CNN/이론/CNN (이론).pdf",
    "obsidian/ComputerScience/인공지능/5. CNN/이론/CNN 주요설계모듈(이론).pdf",
    "obsidian/ComputerScience/컴퓨터 구조/5. 기억 장치/1. 기억 장치 시스템의 개요.md",
    "image/Pasted image 20240520173752.png",
    "image/Pasted image 20240520192341.png",
    "image/Pasted image 20240520200647.png",
    "image/Pasted image 20240520200228.png",
    "image/Pasted image 20240520195649.png",
    "image/Pasted image 20240520195647.png",
    "image/Pasted image 20240520194414.png",
    "image/Pasted image 20240520194358.png",
    "image/Pasted image 20240520194237.png",
    "image/Pasted image 20240520193257.png",
    "obsidian/ComputerScience/컴퓨터 구조/4. 제어 장치/5. 파이프 라이닝.md",
    "obsidian/ComputerScience/컴퓨터 구조/4. 제어 장치/4. 프로세서 제어.md",
    "obsidian/ComputerScience/컴퓨터 구조/4. 제어 장치/1. 제어 장치의 기능.md",
    "obsidian/ComputerScience/컴퓨터 구조/4. 제어 장치/3. 명령어 사이클.md",
    "obsidian/ComputerScience/컴퓨터 구조/4. 제어 장치/2. 제어 장치의 종류.md",
    "무제 파일.md",
    "obsidian/ComputerScience/컴퓨터 구조/3. 중앙 처리 장치/1. 프로세스 구성과 동작.md",
    "obsidian/ComputerScience/컴퓨터 구조/3. 중앙 처리 장치/6. CISC와 RISC.md",
    "obsidian/ComputerScience/컴퓨터 구조/3. 중앙 처리 장치/애플 M4 CPU/애플 M4 CPU.md",
    "obsidian/ComputerScience/컴퓨터 구조/3. 중앙 처리 장치/4. 컴퓨터 명령어.md",
    "obsidian/ComputerScience/컴퓨터 구조/3. 중앙 처리 장치/5. 주소 지정 방식.md",
    "obsidian/ComputerScience/컴퓨터 구조/3. 중앙 처리 장치/2. 산술 논리 연산 장치.md",
    "obsidian/ComputerScience/컴퓨터 구조/3. 중앙 처리 장치/3. 레지스터.md",
    "obsidian/ComputerScience/데이터 구조/트리 (TREE).md",
    "무제 파일.canvas"
  ]
}