{
  "main": {
    "id": "c18b2700cdefe54e",
    "type": "split",
    "children": [
      {
        "id": "d1bf71903097a1fc",
        "type": "tabs",
        "children": [
          {
            "id": "58d687086c7687de",
            "type": "leaf",
            "state": {
              "type": "markdown",
              "state": {
                "file": "obsidian/ComputerScience/확률과 통계/Probability/Probability.md",
                "mode": "source",
                "source": false
              }
            }
          }
        ]
      }
    ],
    "direction": "vertical"
  },
  "left": {
    "id": "d4ef660eefc9dce8",
    "type": "split",
    "children": [
      {
        "id": "6a40ddeab999d131",
        "type": "tabs",
        "children": [
          {
            "id": "4824d7b5ee6b90fb",
            "type": "leaf",
            "state": {
              "type": "file-explorer",
              "state": {
                "sortOrder": "alphabetical"
              }
            }
          },
          {
            "id": "7cea1b4cbc945680",
            "type": "leaf",
            "state": {
              "type": "search",
              "state": {
                "query": "",
                "matchingCase": false,
                "explainSearch": false,
                "collapseAll": false,
                "extraContext": false,
                "sortOrder": "alphabetical"
              }
            }
          },
          {
            "id": "998b39b375eb1994",
            "type": "leaf",
            "state": {
              "type": "bookmarks",
              "state": {}
            }
          }
        ]
      }
    ],
    "direction": "horizontal",
    "width": 244.5
  },
  "right": {
    "id": "7955a80cb3f4ce08",
    "type": "split",
    "children": [
      {
        "id": "74a2a58bda4cda75",
        "type": "tabs",
        "children": [
          {
            "id": "d44099825c849e5a",
            "type": "leaf",
            "state": {
              "type": "backlink",
              "state": {
                "file": "obsidian/ComputerScience/확률과 통계/Probability/Probability.md",
                "collapseAll": false,
                "extraContext": false,
                "sortOrder": "alphabetical",
                "showSearch": false,
                "searchQuery": "",
                "backlinkCollapsed": false,
                "unlinkedCollapsed": true
              }
            }
          },
          {
            "id": "d0d8bbe68caebe73",
            "type": "leaf",
            "state": {
              "type": "outgoing-link",
              "state": {
                "file": "obsidian/ComputerScience/확률과 통계/Probability/Probability.md",
                "linksCollapsed": false,
                "unlinkedCollapsed": true
              }
            }
          },
          {
            "id": "6ddf4ffb0a43ab89",
            "type": "leaf",
            "state": {
              "type": "tag",
              "state": {
                "sortOrder": "frequency",
                "useHierarchy": true
              }
            }
          },
          {
            "id": "e26efddcf6394f13",
            "type": "leaf",
            "state": {
              "type": "outline",
              "state": {
                "file": "obsidian/ComputerScience/확률과 통계/Probability/Probability.md"
              }
            }
          }
        ],
        "currentTab": 1
      }
    ],
    "direction": "horizontal",
    "width": 200,
    "collapsed": true
  },
  "left-ribbon": {
    "hiddenItems": {
      "switcher:퀵 스위처 열기": false,
      "graph:그래프 뷰 열기": false,
      "canvas:새 캔버스 만들기": false,
      "daily-notes:오늘의 데일리 노트 열기": false,
      "templates:템플릿 삽입": false,
      "command-palette:명령어 팔레트 열기": false,
      "obsidian-excalidraw-plugin:Create new drawing": false,
      "templater-obsidian:Templater": false
    }
  },
  "active": "4824d7b5ee6b90fb",
  "lastOpenFiles": [
    "obsidian/ComputerScience/확률과 통계/Independence",
    "obsidian/ComputerScience/확률과 통계/Bayes' theorem/Bayes' Theorem 문제.pdf",
    "obsidian/ComputerScience/확률과 통계/Bayes' theorem",
    "obsidian/ComputerScience/확률과 통계/Conditional Probability/Conditional Probability 문제.pdf",
    "obsidian/ComputerScience/확률과 통계/Conditional Probability",
    "obsidian/ComputerScience/확률과 통계/Probability/Probability 문제.pdf",
    "obsidian/ComputerScience/확률과 통계/Probability",
    "obsidian/ComputerScience/확률과 통계/Counting/Counting.md",
    "obsidian/ComputerScience/확률과 통계/Combinations/Combinations.md",
    "obsidian/ComputerScience/확률과 통계/Combinations/Combinations 문제.pdf",
    "obsidian/ComputerScience/확률과 통계/Counting/Counting 문제.pdf",
    "obsidian/ComputerScience/확률과 통계/Counting/Permutations 문제.pdf",
    "obsidian/ComputerScience/확률과 통계/Combinations",
    "obsidian/ComputerScience/확률과 통계/Bayes' theorem/Bayes' Theorem.md",
    "obsidian/ComputerScience/Python(basic)/리스트, 튜플, 딕셔너리.md",
    "obsidian/ComputerScience/데이터 구조/이중 연결 리스트.md",
    "obsidian/ComputerScience/웹프로그래밍/Spring Boot 기초/연습문제.md",
    "obsidian/ComputerScience/웹프로그래밍/Spring Boot 개발 환경 세팅/연습문제.md",
    "obsidian/ComputerScience/웹프로그래밍/HTML 기초/연습문제.md",
    "obsidian/ComputerScience/웹프로그래밍/Spring Boot 기초/Spring Boot 기초 실습.md",
    "obsidian/ComputerScience/웹프로그래밍/Space for Practice and Creation.md",
    "obsidian/ComputerScience/웹프로그래밍/HTML 기초/HTML 기초 실습.md",
    "obsidian/ComputerScience/데이터 구조/원형 연결 리스트.md",
    "obsidian/ComputerScience/데이터 구조/스택.md",
    "obsidian/ComputerScience/데이터 구조/단순 연결 리스트.md",
    "obsidian/ComputerScience/인공지능/Perceptron/실습/AND, NAND, OR 게이트.md",
    "obsidian/ComputerScience/인공지능/MLP(Multi Layer Perceptron)/이론/MLP theorm.md",
    "obsidian/ComputerScience/인공지능/MLP(Multi Layer Perceptron)/실습/MLP (Multi Layer Perceptron).md",
    "obsidian/ComputerScience/인공지능/MLP(Multi Layer Perceptron)/실습/SLP (Single Layer Perceptron).md",
    "obsidian/ComputerScience/인공지능/Backpropagation/이론/Backpropagation.md",
    "obsidian/index.md",
    "obsidian/ComputerScience/컴퓨터 구조 (pdf 우선)/디지털 논리 회로/카르노 맵.md",
    "obsidian/ComputerScience/컴퓨터 구조 (pdf 우선)/디지털 논리 회로/조합 논리 회로.md",
    "obsidian/ComputerScience/컴퓨터 구조 (pdf 우선)/디지털 논리 회로/불 대수.md",
    "obsidian/ComputerScience/컴퓨터 구조 (pdf 우선)/디지털 논리 회로/논리 게이트.md",
    "obsidian/ComputerScience/컴퓨터 구조 (pdf 우선)/데이터의 표현/진법과 진법 변환.md",
    "무제 파일.canvas"
  ]
}